{
  "posts": [
    {
      "id": "id0",
      "title": "자바 공부",
      "writer": "이희찬",
      "content": "객체지향 프로그래밍은 재밌습니다."
    },
    {
      "id": "id1",
      "title": "루씬 공부",
      "writer": "홍길동",
      "content": "루씬은 아파치에서 만든 오픈 소스입니다."
    },
    {
      "id": "id2",
      "title": "디비 공부",
      "writer": "신사임당",
      "content": "NoSQL은 데이터베이스의 종류다."
    },
    {
      "id": "id3",
      "title": "식사",
      "writer": "이희찬",
      "content": "점심 식사시간 전에는 배가 고프다."
    },
    {
      "id": "id4",
      "title": "자유시간",
      "writer": "이희찬",
      "content": "카페에서의 담콤한 휴식"
    },
    {
      "id": "id5",
      "title": "심심해",
      "writer": "문광제",
      "content": "심심해 죽겠습니다."
    },
    {
      "id": "id6",
      "title": "취준생",
      "writer": "문광제",
      "content": "취업을 준비하고 있다기 보다는 그냥 놀고 있습니다."
    },
    {
      "id": "id7",
      "title": "심심합니다.",
      "writer": "심심이",
      "content": "나랑 놀사람 손들어~"
    },
    {
      "id": "id8",
      "title": "공부 열심히 해보까",
      "writer": "이희찬",
      "content": "공부를 열심히 하기 위해서는 마음가짐이 필요합니다."
    },
    {
      "id": "id9",
      "title": "인턴 3주 남음",
      "writer": "문광제",
      "content": "인턴이 3주 남았습니다."
    },
    {
      "id": "id10",
      "title": "인턴 5주 남음",
      "writer": "이희찬",
      "content": "인턴이 5주 남았습니다."
    },
    {
      "id": "id11",
      "title": "N646",
      "writer": "포시에스",
      "content": "산미가 있는 커피가 저희 커피의 장점입니다."
    },
    {
      "id": "id12",
      "title": "쓴 커피",
      "writer": "스타벅스",
      "content": "아무래도 쓴 커피를 좋아하는 고객들이 많은 것 같습니다."
    },
    {
      "id": "id13",
      "title": "산미가 있는 커피",
      "writer": "N646",
      "content": "스타벅스 커피는 저희랑 정반대입니다."
    },
    {
      "id": "id14",
      "title": "학교",
      "writer": "교장선생님",
      "content": "코로나가 위험함으로 조심하시기 바랍니다."
    },
    {
      "id": "id15",
      "title": "코로나",
      "writer": "방역대책위원회",
      "content": "코로나를 조심해 주세용"
    }
  ]
}